odoo/addons/auth_totp/README.rst
odoo/addons/auth_totp/__init__.py
odoo/addons/auth_totp/__manifest__.py
odoo/addons/auth_totp/exceptions.py
odoo/addons/auth_totp/controllers/__init__.py
odoo/addons/auth_totp/controllers/main.py
odoo/addons/auth_totp/data/ir_config_parameter.xml
odoo/addons/auth_totp/i18n/am.po
odoo/addons/auth_totp/i18n/ar.po
odoo/addons/auth_totp/i18n/auth_totp.pot
odoo/addons/auth_totp/i18n/bg.po
odoo/addons/auth_totp/i18n/bs.po
odoo/addons/auth_totp/i18n/ca.po
odoo/addons/auth_totp/i18n/ca_ES.po
odoo/addons/auth_totp/i18n/cs.po
odoo/addons/auth_totp/i18n/da.po
odoo/addons/auth_totp/i18n/de.po
odoo/addons/auth_totp/i18n/el_GR.po
odoo/addons/auth_totp/i18n/en_AU.po
odoo/addons/auth_totp/i18n/en_GB.po
odoo/addons/auth_totp/i18n/es.po
odoo/addons/auth_totp/i18n/es_AR.po
odoo/addons/auth_totp/i18n/es_CL.po
odoo/addons/auth_totp/i18n/es_CO.po
odoo/addons/auth_totp/i18n/es_CR.po
odoo/addons/auth_totp/i18n/es_DO.po
odoo/addons/auth_totp/i18n/es_EC.po
odoo/addons/auth_totp/i18n/es_ES.po
odoo/addons/auth_totp/i18n/es_MX.po
odoo/addons/auth_totp/i18n/es_PE.po
odoo/addons/auth_totp/i18n/es_PY.po
odoo/addons/auth_totp/i18n/es_VE.po
odoo/addons/auth_totp/i18n/et.po
odoo/addons/auth_totp/i18n/eu.po
odoo/addons/auth_totp/i18n/fa.po
odoo/addons/auth_totp/i18n/fi.po
odoo/addons/auth_totp/i18n/fr.po
odoo/addons/auth_totp/i18n/fr_CA.po
odoo/addons/auth_totp/i18n/fr_CH.po
odoo/addons/auth_totp/i18n/fr_FR.po
odoo/addons/auth_totp/i18n/gl.po
odoo/addons/auth_totp/i18n/gl_ES.po
odoo/addons/auth_totp/i18n/he.po
odoo/addons/auth_totp/i18n/hi.po
odoo/addons/auth_totp/i18n/hr.po
odoo/addons/auth_totp/i18n/hr_HR.po
odoo/addons/auth_totp/i18n/hu.po
odoo/addons/auth_totp/i18n/id.po
odoo/addons/auth_totp/i18n/it.po
odoo/addons/auth_totp/i18n/ja.po
odoo/addons/auth_totp/i18n/ko.po
odoo/addons/auth_totp/i18n/lo.po
odoo/addons/auth_totp/i18n/lt.po
odoo/addons/auth_totp/i18n/lt_LT.po
odoo/addons/auth_totp/i18n/lv.po
odoo/addons/auth_totp/i18n/mk.po
odoo12_addon_auth_totp-12.0.1.1.0.dist-info/METADATA
odoo12_addon_auth_totp-12.0.1.1.0.dist-info/WHEEL
odoo12_addon_auth_totp-12.0.1.1.0.dist-info/top_level.txt
odoo12_addon_auth_totp-12.0.1.1.0.dist-info/RECORD
