Metadata-Version: 2.1
Name: odoo12-addon-auth-totp
Version: 12.0.1.1.0
Summary: Allows users to enable MFA and add optional trusted devices
Home-page: https://github.com/OCA/server-auth
Author: LasLabs, Odoo Community Association (OCA)
Author-email: support@odoo-community.org
License: LGPL-3
Platform: UNKNOWN
Classifier: Programming Language :: Python
Classifier: Framework :: Odoo
Classifier: License :: OSI Approved :: GNU Lesser General Public License v3 (LGPLv3)
Requires-Python: >=3.5
Requires-Dist: odoo (<12.1dev,>=12.0a)
Requires-Dist: pyotp
